MANIFEST.in
PluginFixedQuickOpen.py
setup.cfg
setup.py
scribes.file.quick_open_fix.egg-info/PKG-INFO
scribes.file.quick_open_fix.egg-info/SOURCES.txt
scribes.file.quick_open_fix.egg-info/dependency_links.txt
scribes.file.quick_open_fix.egg-info/not-zip-safe
scribes.file.quick_open_fix.egg-info/top_level.txt