Metadata-Version: 1.0
Name: scribes.file.quick-open-fix
Version: 0.2.1
Summary: Scribes plugin. Adds project support to stock quick open plugin
Home-page: http://github.com/baverman/scribes-goodies
Author: Anton Bobrov
Author-email: bobrov@vl.ru
License: UNKNOWN
Platform: UNKNOWN
